mlforecast/__init__.py
mlforecast/_modidx.py
mlforecast/auto.py
mlforecast/callbacks.py
mlforecast/compat.py
mlforecast/core.py
mlforecast/feature_engineering.py
mlforecast/flavor.py
mlforecast/forecast.py
mlforecast/grouped_array.py
mlforecast/lag_transforms.py
mlforecast/lgb_cv.py
mlforecast/optimization.py
mlforecast/py.typed
mlforecast/target_transforms.py
mlforecast/utils.py
mlforecast/distributed/__init__.py
mlforecast/distributed/forecast.py
mlforecast/distributed/models/__init__.py
mlforecast/distributed/models/dask/__init__.py
mlforecast/distributed/models/dask/lgb.py
mlforecast/distributed/models/dask/xgb.py
mlforecast/distributed/models/ray/__init__.py
mlforecast/distributed/models/ray/lgb.py
mlforecast/distributed/models/ray/xgb.py
mlforecast/distributed/models/spark/__init__.py
mlforecast/distributed/models/spark/lgb.py
mlforecast/distributed/models/spark/xgb.py
mlforecast-1.0.1.dist-info/LICENSE
mlforecast-1.0.1.dist-info/METADATA
mlforecast-1.0.1.dist-info/WHEEL
mlforecast-1.0.1.dist-info/entry_points.txt
mlforecast-1.0.1.dist-info/top_level.txt
mlforecast-1.0.1.dist-info/RECORD
