Metadata-Version: 2.2
Name: mlforecast
Version: 1.0.1
Summary: Scalable machine learning based time series forecasting
Home-page: https://github.com/Nixtla/mlforecast
Author: José Morales
Author-email: jmoralz92@gmail.com
License: Apache Software License 2.0
Keywords: python forecast forecasting machine-learning dask
Classifier: Development Status :: 5 - Production/Stable
Classifier: Intended Audience :: Developers
Classifier: Natural Language :: English
Classifier: Programming Language :: Python :: 3.9
Classifier: Programming Language :: Python :: 3.10
Classifier: Programming Language :: Python :: 3.11
Classifier: Programming Language :: Python :: 3.12
Classifier: Programming Language :: Python :: 3.13
Classifier: License :: OSI Approved :: Apache Software License
Requires-Python: >=3.9
License-File: LICENSE
Requires-Dist: cloudpickle
Requires-Dist: coreforecast>=0.0.15
Requires-Dist: fsspec
Requires-Dist: optuna
Requires-Dist: pandas
Requires-Dist: scikit-learn
Requires-Dist: utilsforecast>=0.2.9
Provides-Extra: dask
Requires-Dist: fugue; extra == "dask"
Requires-Dist: dask[complete]; extra == "dask"
Requires-Dist: lightgbm; extra == "dask"
Requires-Dist: xgboost; extra == "dask"
Provides-Extra: ray
Requires-Dist: fugue[ray]; extra == "ray"
Requires-Dist: lightgbm_ray; extra == "ray"
Requires-Dist: xgboost_ray; extra == "ray"
Provides-Extra: spark
Requires-Dist: fugue; extra == "spark"
Requires-Dist: pyspark>=3.3; extra == "spark"
Requires-Dist: lightgbm; extra == "spark"
Requires-Dist: xgboost; extra == "spark"
Provides-Extra: aws
Requires-Dist: fsspec[s3]; extra == "aws"
Provides-Extra: azure
Requires-Dist: fsspec[adl]; extra == "azure"
Provides-Extra: gcp
Requires-Dist: fsspec[gcs]; extra == "gcp"
Provides-Extra: polars
Requires-Dist: polars[numpy]; extra == "polars"
Provides-Extra: dev
Requires-Dist: black>=24; extra == "dev"
Requires-Dist: datasetsforecast>=1; extra == "dev"
Requires-Dist: gitpython; extra == "dev"
Requires-Dist: holidays<0.21; extra == "dev"
Requires-Dist: lightgbm; extra == "dev"
Requires-Dist: matplotlib; extra == "dev"
Requires-Dist: mlflow>=2.10.0; extra == "dev"
Requires-Dist: mypy; extra == "dev"
Requires-Dist: nbdev<2.3.26; extra == "dev"
Requires-Dist: numpy>=2; extra == "dev"
Requires-Dist: pandas>=2.2.2; extra == "dev"
Requires-Dist: pre-commit; extra == "dev"
Requires-Dist: polars[numpy]; extra == "dev"
Requires-Dist: pyarrow; extra == "dev"
Requires-Dist: ruff; extra == "dev"
Requires-Dist: setuptools; extra == "dev"
Requires-Dist: statsmodels; extra == "dev"
Requires-Dist: xgboost; extra == "dev"
Provides-Extra: all
Requires-Dist: mypy; extra == "all"
Requires-Dist: xgboost_ray; extra == "all"
Requires-Dist: matplotlib; extra == "all"
Requires-Dist: holidays<0.21; extra == "all"
Requires-Dist: fsspec[s3]; extra == "all"
Requires-Dist: gitpython; extra == "all"
Requires-Dist: setuptools; extra == "all"
Requires-Dist: fsspec[adl]; extra == "all"
Requires-Dist: ruff; extra == "all"
Requires-Dist: lightgbm; extra == "all"
Requires-Dist: polars[numpy]; extra == "all"
Requires-Dist: xgboost; extra == "all"
Requires-Dist: mlflow>=2.10.0; extra == "all"
Requires-Dist: fsspec[gcs]; extra == "all"
Requires-Dist: pyspark>=3.3; extra == "all"
Requires-Dist: fugue[ray]; extra == "all"
Requires-Dist: numpy>=2; extra == "all"
Requires-Dist: pre-commit; extra == "all"
Requires-Dist: pyarrow; extra == "all"
Requires-Dist: nbdev<2.3.26; extra == "all"
Requires-Dist: pandas>=2.2.2; extra == "all"
Requires-Dist: dask[complete]; extra == "all"
Requires-Dist: datasetsforecast>=1; extra == "all"
Requires-Dist: fugue; extra == "all"
Requires-Dist: statsmodels; extra == "all"
Requires-Dist: black>=24; extra == "all"
Requires-Dist: lightgbm_ray; extra == "all"
Dynamic: author
Dynamic: author-email
Dynamic: classifier
Dynamic: description
Dynamic: description-content-type
Dynamic: home-page
Dynamic: keywords
Dynamic: license
Dynamic: provides-extra
Dynamic: requires-dist
Dynamic: requires-python
Dynamic: summary
